<?xml version="1.0" encoding="UTF-8"?>
<?xml-model href="https://pds.nasa.gov/pds4/pds/v1/PDS4_PDS_1B00.sch" schematypens="http://purl.oclc.org/dsdl/schematron"?>
<Product_Context xmlns="http://pds.nasa.gov/pds4/pds/v1"
 xmlns:pds="http://pds.nasa.gov/pds4/pds/v1"  xmlns:xsi="http://www.w3.org/2001/XMLSchema-instance"
 xsi:schemaLocation="http://pds.nasa.gov/pds4/pds/v1 https://pds.nasa.gov/pds4/pds/v1/PDS4_PDS_1B00.xsd">
    
    <Identification_Area>
        <logical_identifier>urn:nasa:pds:context:instrument:vega1.sp1</logical_identifier>
        <version_id>1.0</version_id>
        <title>DUST IMPACT PLASMA DETECTOR for VEGA1</title>
        <information_model_version>1.11.0.0</information_model_version>
        <product_class>Product_Context</product_class>
        <Alias_List>
            <Alias><alternate_title>urn:nasa:pds:context:instrument:sp1.vega1</alternate_title></Alias>  <!-- deprecated LID -->
        </Alias_List>
        <Modification_History>
            <Modification_Detail>
                <modification_date>2021-02-24</modification_date>
                <version_id>1.0</version_id>
                <description>
                    Changed inst LIDs from
                      u:n:p:c:i:instID.scID to
                      u:n:p:c:i:scID.instID
                    And per "Guide toPDS4 Context Products" v1.7,
                    changed all lidvid_reference to lid_reference
                </description>
            </Modification_Detail>
        </Modification_History>
    </Identification_Area>

    <Reference_List>
        <Internal_Reference>
            <lid_reference>urn:nasa:pds:context:instrument_host:spacecraft.vega1</lid_reference>
            <reference_type>instrument_to_instrument_host</reference_type>
        </Internal_Reference>
        <External_Reference>
            <reference_text>
                   Reinhard, R and B. Battrick (eds), &apos;Space Missions to Halley&apos;s Comet&apos;, European
                   Space Agency ESA SP-1066, ESA Pub Div, Moordwijk, Netherlands, 1986.
            </reference_text>
            <description>reference.ESA-SP1066</description>
        </External_Reference>
    </Reference_List>
    
    <Instrument>
        <name>DUST IMPACT PLASMA DETECTOR</name>
        <type>Particle Detector</type> <!--RChen/EN was Electrode Collector-->
        <naif_instrument_id>not applicable</naif_instrument_id>

        <serial_number>not applicable</serial_number>

        <description>
 
 
    Instrument Overview
    ===================
 
    This instrument detects the electric charges
    contained in the plasma cloud generated by a solid
    particle impacting on a gold target.  The principle
    of this technique is similar to that adopted for the
    impact plasma detectors of SP-2.  The magnitude of
    the positive and negative charges is proportional to
    the mass of the particle Q=Am, where A= 10**3C/s for
    an impact velocity of 78 km/s.  The SP-1 system
    includes two similar detectors.  Each unit is made up
    of a base plate (1) covered by a gold target (2) at
    zero potential, perpendicular to the dust flow, and
    an array of strip collectors (4).  The collectors are
    parallel to the dust flow; they are mounted on an
    insulator (3) and their edge is protected from
    impacts by a shield (5) connected electrically to the
    structure.  Adjacent collectors are biased at
    potentials of 30 V, with opposite polarities.  The
    two sets of electrodes in each detector detect a
    positive and a negative current pulse, which are
    analysed and recorded by the electronics unit.  The
    entrance to one detector is covered by a plastic
    foil, to obtain additional information on density
    and/or calibration factor.  The characteristic
    parameters of SP-1 are given in Table 8.
 
 
 
-----------------------------------------------------------------
Table 8. Dust Particle Impact Plasma Detector characteristics
 
Target material         Gold (0.1 mm)
Toil sensor area        160 cm**2, one sensor covered with 0.6 and
                        2 micro m thick plastic foil
                        on Vegas-1 and 2, resp.
Impact charge range     3x10**-14  -10**-8 C
Estimated mass range    3x10**-17  -10**-11 g
Integration time        2 s (high data rate)
                        2.5 min (low data rate)
----------------------------------------------------------------
 
 

        </description>
    </Instrument>
</Product_Context>
