<?xml version="1.0" encoding="UTF-8"?>
<?xml-model href="https://pds.nasa.gov/pds4/pds/v1/PDS4_PDS_1B00.sch" schematypens="http://purl.oclc.org/dsdl/schematron"?>
<Product_Context xmlns="http://pds.nasa.gov/pds4/pds/v1"
 xmlns:pds="http://pds.nasa.gov/pds4/pds/v1"  xmlns:xsi="http://www.w3.org/2001/XMLSchema-instance"
 xsi:schemaLocation="http://pds.nasa.gov/pds4/pds/v1 https://pds.nasa.gov/pds4/pds/v1/PDS4_PDS_1B00.xsd">
    
    <Identification_Area>
        <logical_identifier>urn:nasa:pds:context:instrument:vega1.tnm</logical_identifier>
        <version_id>1.0</version_id>
        <title>TUNDE-M ENERGETIC PARTICLE ANALYZER for VEGA1</title>
        <information_model_version>1.11.0.0</information_model_version>
        <product_class>Product_Context</product_class>
        <Alias_List>
            <Alias><alternate_title>urn:nasa:pds:context:instrument:tnm.vega1</alternate_title></Alias>  <!-- deprecated LID -->
        </Alias_List>
        <Modification_History>
            <Modification_Detail>
                <modification_date>2021-02-24</modification_date>
                <version_id>1.0</version_id>
                <description>
                    Changed inst LIDs from
                      u:n:p:c:i:instID.scID to
                      u:n:p:c:i:scID.instID
                    And per "Guide toPDS4 Context Products" v1.7,
                    changed all lidvid_reference to lid_reference
                </description>
            </Modification_Detail>
        </Modification_History>
    </Identification_Area>

    <Reference_List>
        <Internal_Reference>
            <lid_reference>urn:nasa:pds:context:instrument_host:spacecraft.vega1</lid_reference>
            <reference_type>instrument_to_instrument_host</reference_type>
        </Internal_Reference>
        <External_Reference>
            <reference_text>
                   Reinhard, R and B. Battrick (eds), &apos;Space Missions to Halley&apos;s Comet&apos;, European
                   Space Agency ESA SP-1066, ESA Pub Div, Moordwijk, Netherlands, 1986.
            </reference_text>
            <description>reference.ESA-SP1066</description>
        </External_Reference>
        <External_Reference>
            <reference_text>
                   Gribov, B.E., K. Kecskemety, R.Z. Sagdeev, V.D. Shapiro, V.I. Shevchenko,
                   A.J. Somogyi, K. Szego, G. Erdos, E.G. Eroshenko, K.I. Gringauz, E.
                   Keppler, R.G. Marsden, A.P. Remizov, A.K. Richter, W. Riedler, K.
                   Schwingenschuh, and K.P. Wenzel, Astronomy and Astrophysics, 187, 293-296,
                   1987.
            </reference_text>
            <description>reference.GRIBOVETAL1987</description>
        </External_Reference>
        <External_Reference>
            <reference_text>
                   Kecskementy, K., and T.E. Cravens, Journal of Geophysical Research, 97,
                   2891-2906, 1992.
            </reference_text>
            <description>reference.KECSKEMENTY-CRAVEN92</description>
        </External_Reference>
        <External_Reference>
            <reference_text>
                   Kecskementy K., T.E. Cravens, V.V. Afonin, G. Erdos, E.G. Eroshenko, L.
                   Gan, T.I. Gombosi, K.I. Gringauz, E. Keppler, I.N. Klimenko, R.G. Marsden,
                   A.F. Nagy, A.P. Remizov, A.K. Richter, W. Riedler, K. Schwingenschuh, A.J.
                   Somogyi, K. Szego, M. Tatrallyay, A. Varga, M.I. Verigin, and K.P. Wenzel,
                   Energetic Pick-up Ions Outside the Comet Halley Bow Shock, ESA SP-250, Vol
                   I, 109, 1986.
            </reference_text>
            <description>reference.KECSKEMENTYETAL1986</description>
        </External_Reference>
        <External_Reference>
            <reference_text>
                   Kecskementy K., T.E. Cravens, V.V. Afonin, G. Erdos, E.G. Eroshenko, L.
                   Gan, T.I. Gombosi, K.I. Gringauz, E. Keppler, I.N. Klimenko, R.G. Marsden,
                   A.F. Nagy, A.P. Remizov, A.K. Richter, W. Riedler, K. Schwingenschuh, A.J.
                   Somogyi, K. Szego, M. Tatrallyay, A. Varga, M.I. Verigin, and K.P. Wenzel,
                   Measurements of Energetic Cometary Ions in the Solar Wind in the Preshock
                   Region of Comet Halley, Cosmic Research, 25, 733-742, 1987.
            </reference_text>
            <description>reference.KECSKEMENTYETAL1987</description>
        </External_Reference>
        <External_Reference>
            <reference_text>
                   &apos;Encounters with Comet Halley, The first results&apos;, Nature, Volume 321, No.
                   6067, 15 May 1986.
            </reference_text>
            <description>reference.NATURE321</description>
        </External_Reference>
        <External_Reference>
            <reference_text>
                   Somogyi, A., L. Szabo, V.V. Afonin, A. Banfalvi, J. Ero, M. Farago, T.
                   Gombosi, K.I. Gringauz, K. Kecskemety, E. Keppler, I.N. Klimenko, T.
                   Kovacs, G. Kozma, Yu.I. Logachev, L. Lohonyai, R. Marsden, R. Redl, A.P.
                   Remizov, A. Richter, G.A. Skuridin, V.G. Stolpovskii, Szepesvary, I.
                   T-Szucs, A. Varga, G.A. Vladimirova, K.P. Wenzel, and J. Windberg, Tunde-M
                   Apparatus of the SPF Unit of the Vega Program, in Cometary Exploration III,
                   Gombosi, T.I. (ed.), 351-360, 1983.
            </reference_text>
            <description>reference.SOMOGYIETAL1983</description>
        </External_Reference>
        <External_Reference>
            <reference_text>
                   Somogyi, A., V.V. Afonin, G. Erdos, J. Ero, T. Gombosi, K.I. Gringauz, K.
                   Kecskemety, E. Keppler, I.N. Klimenko, T. Kovacs, G. Kozma, Logachev, L.
                   Lohonyai, R. Marsden, A.P. Remizov, A.K. Richter, G.A. Skuridin, V.G.
                   Stolpovskii, L. Szabo, K. Szego, I. Szentpetery, I. T-Szucs, A. Szepesvary,
                   M. Tatrallyay, A. Varga, M.I. Verigin, K.P. Wenzel, J. Windberg, and G.A.
                   Vladimirova, First Results of High Energy Particle Measurements with the
                   Tunde-M Telescopes on board of the S/C Vega-1 and -2, Field, Particle, and
                   Wave-Experiments on Cometary Missions, Schwingenschuh, K. and W. Riedler
                   (eds.), 237-247, 1985.
            </reference_text>
            <description>reference.SOMOGYIETAL1985</description>
        </External_Reference>
        <External_Reference>
            <reference_text>
                   Somogyi A.J., K.I. Gringauz, K. Szego, L. Szabo, G. Kozma, A.P. Remizov, J.
                   Ero Jr., I.N. Klimenko, I. T-Szucs, M.I. Verigin, J. Windberg, T.E.
                   Cravens, A. Dyachkov, G. Erdos, M. Farago, T.I. Gombosi, K. Kecskementy, E.
                   Keppler, T. Kovacs Jr., A. Kondor, Yu.I. Logachev, L. Lohonyai, R. Marsden,
                   R. Redl, A.K. Richter, V.G. Stolpovskii, J. Szabo, I. Szentpetery, A.
                   Szepesvary, M. Tatrallyay, A. Varga, G.A. Vladimirova, K.P. Wenzel, and A.
                   Zarandy, First Observations of Energetic Particles Near Comet Halley,
                   Nature, 321, 285-287, 1986.
            </reference_text>
            <description>reference.SOMOGYIETAL1986</description>
        </External_Reference>
        <External_Reference>
            <reference_text>
                   Somogyi, A.J., G. Erdos, K. Kecskementy, M. Tatrallyay, A. Varga, Yu.I.
                   Logachev, V.G. Stolpovskii, K.I. Gringauz, I.N. Klimenko, A.P. Remizov,
                   M.I. Verigin, G.A. Vladimirova, E. Keppler, A.K. Richter, R. Marsden, and
                   K.P. Wenzel, Energetic Particle Measurements on Probe Vega-1 and -2:
                   Recurrent Events in the Period December 23, 1984 - April 14, 1985,
                   Proceedings of the 20th International Cosmic Ray Conference, Moscow 1987,
                   Vol IV, 27-30, 1987.
            </reference_text>
            <description>reference.SOMOGYIETAL1987</description>
        </External_Reference>
        <External_Reference>
            <reference_text>
                   Somogyi, A.J., W.I. Axford, G. Erdos, W.H. Ip, V.D. Shapiro, and V.I.
                   Shevchenko, Particle Acceleration in the Plasma Fields Near Comet Halley,
                   Comet Halley: Investigations, Results, Interpretations, Ellis Horwood
                   Limited, Chichester, England, Vol I, 203-219, 1990.
            </reference_text>
            <description>reference.SOMOGYIETAL1990</description>
        </External_Reference>
    </Reference_List>
    
    <Instrument>
        <name>TUNDE-M ENERGETIC PARTICLE ANALYZER</name>
        <type>Particle Detector</type> <!--RChen/EN was Plasma Experiment. From JSH's xl file-->
        <naif_instrument_id>not applicable</naif_instrument_id>

        <serial_number>not applicable</serial_number>

        <description>
 
 
    Instrument Overview
    ===================
 
      The prime objective of the energetic-particle
      analyzer is to measure the energy and flux of the
      cometary ions that might be accelerated by, for
      example, solar-wind magnetic fields.  Two similar
      telescopes provide information about the angular
      distribution of the ion flux.  The first telescope,
      T1 is viewing at 55 deg to the east of the Sun;and
      the T2 telescope, looks at 90 deg to the east of
      the Sun, both in the ecliptic plane and
      approximately opposite to the spacecraft velocity
      vector.  Each telescope consists of two silicon
      detectors, A (8 mm in diameter and 0.1 mm thick)
      and B (16 mm in diameter and 1 mm thick), and an
      anti-coincidence scintillation shield.  Electrons
      with energies of less than 0.2 MeV are deflected
      away from the entrance aperture by a magnet.  The
      low-energy (30-640 keV) ions trigger a signal in
      detector A only.  More energetic particles are
      detected in both A and B, and it is possible to
      distinguish between electrons, protons and heavier
      nuclei by comparing the amplitudes of the signals
      delivered by the two detectors.  The characteristic
      parameters of these two telescopes are given in the
      table below.
 
 
 
 Table. Energetic-Particle Analyzer characteristics
 Ion energy range (detector A)
 Resolution                           20 heV-640 keV
 -  range  20-160 keV                 10 keV
 -  range 160-400 keV                 20 keV
 -  range 400-640 keV                 40 keV
 Energy ranges (detectors A and B)
 -  electrons                         0.5-0.75 MeV
 -  protons                           3.2-13 MeV
 -  ions (Z &gt;= 2)                     3.2-13 MeV/nucleon
 Integral flux of protons and nuclei  Energy &gt;/= 13 MeV/nucleon
 Geometrical factor                   0.2 cm**2 sr
 Field of view                        25deg half cone
 Time resolution                      4 s (encounter);
                                      10 or 20 min (cruise)
 
 
      The scientific objective was to study the high
      energy (from about 50 keV to 700 keV) ion
      environment of comet Halley.  Ions (probably mostly
      water group) were successfully observed (for
      details, see Somogyi et al.  Nature 321, 285, 1986;
      Gribov B.E.  et al., Astronomy and Astrophysics
      187, 293 1987; Kecskemety K.  et al., J. Geophys.
      Res.  94, 185, 1989; Somogyi A.J.  et al., in:
      &apos;Comet Halley - Investigations, Results,
      Interpretations&apos;, Ellis Horwood Limited,
      Chichester, England, Vol. 1, 203, 1990; and
      Kecskemety K. and T.E. Cravens, J. Geophys.
      Res. 97, 2891, 1992.)
 
 Calibrations: electronic calibrations were performed
 only, the results were used to determine the relative
 width of the ion energy channels and from this to obtain
 the real values of the energy limits of the channels
 starting from the nominal values.
 
 The instrument was mounted to point in a fixed direction
 relative to the spacecraft.
 
 Principal investigator: Prof. A.J. Somogyi.
 
 Coinvestigators:
 G. Erdos, J. Ero Jr., M. Farago, T.I. Gombosi,
 K. Kecskemety, A. Kondor, T. Kovacs Jr., Gy. Kozma,
 L. Lohonyai, R. Redl, J. Szabo, L. Szabo, K. Szego,
 I. Szentpetery, A. Szepesvary, I. T.-Szucs,
 M. Tatrallyay, A. Varga, J. Windberg,
 A. Zarandy (Central Research Institute for Physics,
 Budapest, Hungary);
 R.Redl (Technical University, Budapest, Hungary);
 T.E. Cravens (Space Physics Research Laboratory,
 University of Michigan, Ann Arbor, USA);
 A. Dyachkov, I.N. Klimenko, A.P. Remizov, M.I. Verigin,
 G.A. Vladimirova (Space Research Institute, Moscow, USSR);
 E. Keppler, A.K. Richter (Max-Planck-Institute
 fur Aeronomie, Katlenburg-Lindau, FRG);
 Yu.I. Logachev, V.G. Stolpovskii (Moscow State
 University, Moscow, USSR)
 R. Marsden, K.-P. Wenzel (Space Science Dept., ESA,
 ESTEC, Noordwijk, The Netherlands).
 
 Instrument Section/ Modes of Operation
 
 TUNDE-M consists of two particle telescopes: T1 is viewing
 at 55 deg to the east of the Sun, T2 looks at 90 deg to
 the east of the Sun, both in the ecliptic plane. The
 telescopes consist of two circular surface barrier
 semiconductor detectors with an Al layer of
 15x10**-6 g/cm**2 coated on the front detector (A)
 and an anticoincidence scintillation detector MCP.
 Low energy electrons (below about 160 keV) were
 deflected with a magnet.
 Field of view (half cone): 25 deg.
 Geometric factor: 0.25 cm**2 sr.
 Particles stopping in the thin front detector were
 not identified (they are referred as ion channels),
 those reaching the thick detector were identified
 via the dE/E method.
 
 T1 was working all along the mission, T2 was rendered
 inoperative before the Halley encounter.
 
 Modes of operation: Trassa-1 and Trassa-2
 (cruise phase) and BRL (fast telemetry, started at
 04:17:03 UT, March 6, 1986, ended at 08:24:53 UT,
 same day). Data were gathered in 66 channels, some
 referred as ions, others as identified particles,
 both between preset energy limits (given at the
 data set description).
 
 Data rate: 1 frame of 66 real numbers in every
 4 s (BRL mode). The measurement was continuous,
 with an integration time of 4 s.
 
 Other technical details can be found in:
 Somogyi A.J. et al., in: Proc. of Int. Conf. on
 Cometary Exploration, Budapest 1982
 (ed. T.I. Gombosi), Vol. 3, p351, 1983
 
 and
 
 Somogyi A.J. et al., in: &apos;Field, particle and
 wave experiments on cometary missions&apos;
 (eds. K. Schwingenschuh and W. Riedler),
 Austrian Academy of Sciences, Proc. of
 International Workshop, Graz, Austria 1985,
 p237, 1986.
 
 Details concerning scientific result were published in:
 Somogyi et al. Nature 321, 285, 1986;
 
 Gribov B.E. et al., Astronomy and Astrophysics 187,
 293 1987;
 
 Kecskemety K. et al., J. Geophys. Res. 94, 185, 1989;
 
 Somogyi A.J. et al., in: &apos;Comet Halley - Investigations,
 Results, Interpretations&apos;, Ellis Horwood Limited,
 Chichester, England, Vol. 1, 203, 1990;
 
 Kecskemety K. and T.E. Cravens, J. Geophys. Res.
 97, 2891, 1992.
 
 

        </description>
    </Instrument>
</Product_Context>
